[{"email":"martuchis@gmail.com","clave":"$2y$10$RcNbIySjy4StM2oefMnlDuPv8dkAjuuwC5BlOidYkPxfTQSKYJ9Pm","imagen":"img\/20200928015451.jpg"},{"email":"moremio","clave":"$2y$10$8jfsWs28BKaQ79H.mNVtQ.I5SKVwO9PbCg2DSweB81OMfb96X\/iLG","imagen":"imagen","tipo":null},{"email":"moremio","clave":"$2y$10$L0y4bblIXE28zlglM.pSeu7QGE\/uOzdSsrsW2a7T.Rblb0OHnoxjS","imagen":"img\/20200929081846.jpg","tipo":null},{"email":"moremio22","clave":"$2y$10$.yk1TIlsRpy4P4gAbQb11ezre6UbTChL53oFN7oDUsIcuy3o7oXYq","imagen":"img\/20200929104817.jpg","tipo":null},{"email":"moremio","clave":"$2y$10$rBK\/I5NjIypVn.UNHaRbFOyAUp25xCLX4zj8zf4BhOg3xqamHNora","imagen":"img\/20200929112033.jpg","tipo":null},{"email":"moremio","clave":"$2y$10$.7hynRJYu3ObwhGmGvHcR.kANf1mFsADCUlPjOaudXDR5yHvgDWke","imagen":"img\/20200929112323.jpg","tipo":null},{"email":"moremio","clave":"$2y$10$UR9Iwe4hiGEEaundhmO.Te7kCXyj.YT58ZmkIQzPy60gMTByhZtQ6","imagen":"img\/20201002024145.jpg","tipo":null},{"email":"moremio","clave":"$2y$10$Zc01zbpxJRumPMmKUO4qkeRj33y1S3at5Jn\/gNEHmGyV6ccvYoPpG","imagen":"img\/20201002024218.jpg","tipo":null}]